pds/__init__.py
pds/ldd_manager/VERSION.txt
pds/ldd_manager/__init__.py
pds/ldd_manager/generate.py
pds/ldd_manager/release.py
pds/ldd_manager/util.py
pds/ldd_manager/validate.py
pds_ldd_manager-2.0.1.dist-info/licenses/LICENSE.md
pds_ldd_manager-2.0.1.dist-info/licenses/NOTICE.txt
pds_ldd_manager-2.0.1.dist-info/METADATA
pds_ldd_manager-2.0.1.dist-info/WHEEL
pds_ldd_manager-2.0.1.dist-info/entry_points.txt
pds_ldd_manager-2.0.1.dist-info/top_level.txt
pds_ldd_manager-2.0.1.dist-info/zip-safe
pds_ldd_manager-2.0.1.dist-info/RECORD
